math2docx/__init__.py
math2docx/main.py
math2docx-2.0.3.dist-info/LICENSE
math2docx-2.0.3.dist-info/METADATA
math2docx-2.0.3.dist-info/WHEEL
math2docx-2.0.3.dist-info/top_level.txt
math2docx-2.0.3.dist-info/RECORD
