Metadata-Version: 2.1
Name: math2docx
Version: 2.0.3
Summary: Open source Python library converting math formula to docx
Home-page: https://github.com/keh9mark/math2docx
Author: Nikolay Markov
Author-email: keh9mark@yandex.ru
License: UNKNOWN
Platform: UNKNOWN
Classifier: Programming Language :: Python :: 3.8
Classifier: License :: OSI Approved :: MIT License
Classifier: Operating System :: OS Independent
Requires-Python: >=3.6
Requires-Dist: latex2mathml
Requires-Dist: mathml2omml
Requires-Dist: python-docx
